studr/__Main__.py
studr/__init__.py
studr-0.3.3.dist-info/licenses/LICENSE
studr-0.3.3.dist-info/METADATA
studr-0.3.3.dist-info/WHEEL
studr-0.3.3.dist-info/entry_points.txt
studr-0.3.3.dist-info/top_level.txt
studr-0.3.3.dist-info/RECORD
