Metadata-Version: 2.4
Name: studr
Version: 0.3.3
Summary: im gonna add a description later
Author-email: fr33 / Emirhan <Emirhan.07274@gmail.com>
License: GPL-3.0-or-later
Project-URL: Homepage, https://github.com/Emirhan-7274/studr
Project-URL: Repository, https://github.com/Emirhan-7274/studr
Project-URL: Issues, https://github.com/Emirhan-7274/studr/issues
Keywords: stopwatch,timer,ascii,art,terminal,timer,cli
Classifier: Development Status :: 4 - Beta
Classifier: Intended Audience :: End Users/Desktop
Classifier: License :: OSI Approved :: GNU General Public License v3 or later (GPLv3+)
Classifier: Operating System :: OS Independent
Classifier: Programming Language :: Python :: 3
Classifier: Programming Language :: Python :: 3.8
Classifier: Programming Language :: Python :: 3.9
Classifier: Programming Language :: Python :: 3.10
Classifier: Programming Language :: Python :: 3.11
Classifier: Programming Language :: Python :: 3.12
Classifier: Topic :: Utilities
Classifier: Topic :: System :: Monitoring
Classifier: Topic :: Multimedia :: Graphics :: Graphics Conversion
Classifier: Environment :: Console
Requires-Python: >=3.8
License-File: LICENSE
Requires-Dist: click>=8.0.0
Requires-Dist: windows-curses>=2.4.1
Requires-Dist: art>=6.0
Requires-Dist: rich>=13.0.0
Requires-Dist: pyfiglet>=0.8.0
Dynamic: license-file
